Workbook

Sheet Rates
A1: German Tax Rates & Parameters — 2025 and 2026 | All blue cells are editable
A2: INCOME TAX — §32a EStG
A3: Parameter | B3: 2025 Value | C3: 2026 Value | D3: Notes
A4: Grundfreibetrag (basic tax-free allowance) | B4: 12096 | C4: 12348 | D4: Source: §32a EStG 2025/2026
A5: Zone 2 upper boundary | B5: 17443 | C5: 17799 | D5: Approx. — zone 2/3 split
A6: Zone 3 upper boundary (42% starts from) | B6: 66760 | C6: 69878 | D6: 42% top rate threshold
A7: Reichensteuer upper (45% starts from) | B7: 277825 | C7: 277825 | D7: §32a EStG Abs.5
A8: Top marginal rate (42%) | B8: 0.42 | C8: 0.42 | D8: Applies above zone 3 boundary
A9: Solidarity surcharge rate | B9: 0.055 | C9: 0.055 | D9: 5.5% of income tax
A10: Soli exemption threshold (income tax amount) | B10: 19950 | C10: 19950 | D10: Exempt if income tax ≤ this
A11: Church tax rate (Bavaria & BW = 8%, others = 9%) | B11: 0.09 | C11: 0.09 | D11: 9% default; Bavaria/BW use 8%
A13: SOCIAL SECURITY CONTRIBUTION RATES (employee share)
A14: Parameter | B14: 2025 Value | C14: 2026 Value | D14: Notes
A15: Pension insurance (Rentenversicherung) — employee | B15: 0.093 | C15: 0.093 | D15: 9.3% of 18.6% total
A16: Health insurance base rate — employee (7.3% of 14.6%) | B16: 0.073 | C16: 0.073 | D16: Same for all public funds
A17: TK Zusatzbeitrag — employee share (TK-specific) | B17: 0.01225 | C17: 0.01345 | D17: 2.45%/2=1.225% (2025); 2.69%/2=1.345% (2026)
A18: TK total health rate (employee) = base + Zusatz | B18: 0.08525 | C18: 0.08645 | D18: Employee half of TK total: 7.3% base + half of 2.45% (2025) or 2.69% (2026)
A19: Long-term care — base (employee) — with child | B19: 0.018 | C19: 0.018 | D19: 1.8% employer always; employee: 1.8% if ≥1 child
A20: Long-term care — childless surcharge (employee) | B20: 0.006 | C20: 0.006 | D20: Additional 0.6% if no children (over 23)
A21: Long-term care — 2nd child reduction per child | B21: 0.0025 | C21: 0.0025 | D21: −0.25% per child (2nd-5th) from employee share
A22: Unemployment insurance (Arbeitslosenversicherung) — employee | B22: 0.013 | C22: 0.013 | D22: 1.3% of 2.6% total
A24: SOCIAL SECURITY CONTRIBUTION CEILINGS (Beitragsbemessungsgrenzen)
A25: Parameter | B25: 2025 Value | C25: 2026 Value | D25: Notes
A26: Health & care insurance ceiling (annual) | B26: 66150 | C26: 69750 | D26: Above = no health/care contributions
A27: Pension & unemployment ceiling (annual) | B27: 96600 | C27: 101400 | D27: Above = no pension/unemp contributions
A28: Compulsory public health insurance limit (JAEG) | B28: 73800 | C28: 77400 | D28: Above = can choose private insurance
A30: LUMP-SUM ALLOWANCES (Pauschbeträge)
A31: Parameter | B31: 2025 Value | C31: 2026 Value | D31: Notes
A32: Employee expense flat-rate (Arbeitnehmer-Pauschbetrag) | B32: 1230 | C32: 1230 | D32: Applied automatically — deduct more only if higher
A33: Saver's allowance — single (Sparer-Pauschbetrag) | B33: 1000 | C33: 1000 | D33: €2,000 for married
A34: Homeoffice-Pauschale (per WFH day) | B34: 6 | C34: 6 | D34: Max 210 days = €1,260/year
A35: Small equipment immediate write-off threshold (net) | B35: 800 | C35: 800 | D35: Below = fully deductible in purchase year
A36: Commuter allowance — per km (first 20km) | B36: 0.3 | C36: 0.3 | D36: 2025: 30¢/km 1st 20km; 2026: 38¢/km from km 1
A37: Commuter allowance — per km (from km 21) | B37: 0.38 | C37: 0.38 | D37: 2025: 38¢ from km 21; 2026: same rate from km 1
A38: Commuter allowance — changeover km (2025=20, 2026=0) | B38: 20 | C38: 0 | D38: 2026: 38¢ applies from km 1
A39: Internet/phone max monthly deduction | B39: 20 | C39: 20 | D39: Max 20% of bill, capped at €20/month
A40: Internet/phone deductible percentage | B40: 0.2 | C40: 0.2 | D40: 20% of monthly bill
A41: Pension contribution max deduction (Sonderausgaben) | B41: 29344 | C41: 29344 | D41: Annual max for pension contributions
A42: Extraordinary burden base rate (zumutbare Belastung) — income 51k-102k, single | B42: 0.03 | C42: 0.03 | D42: 3% of income (bracket 2 of §33 EStG)
A43: Disability flat-rate (Behinderten-Pauschbetrag) GdB 20 | B43: 384 | C43: 384 | D43: GdB 20=384; 30=620; 40=860; 50=1140; 60=1440; 70=1780; 80=2120; 90=2460; 100=2840
... A45: Child benefit (Kindergeld) — per child per month | B45: 255 | C45: 259 | D45: Monthly payment (not a deduction)
A47: CAPITAL GAINS & INVESTMENT INCOME RATES
A48: Parameter | B48: 2025 Value | C48: 2026 Value | D48: Notes
A49: Abgeltungsteuer flat rate on capital gains | B49: 0.25 | C49: 0.25 | D49: 25% flat on dividends, interest, gains
A50: Soli on Abgeltungsteuer | B50: 0.055 | C50: 0.055 | D50: 5.5% of capital gains tax (full rate, always)
A51: Church tax on Abgeltungsteuer | B51: 0 | C51: 0 | D51: If applicable — enter your state's rate
A52: Effective total rate on capital gains (no church) | B52: 0.2638 | C52: 0.2638 | D52: 26.375% = 25% + 5.5% Soli
A54: RENTAL INCOME
A55: Parameter | B55: 2025 Value | C55: 2026 Value | D55: Notes
A56: Depreciation rate for residential property (AfA) | B56: 0.02 | C56: 0.02 | D56: 2% per year on building value (pre-2023 builds)
A57: Depreciation rate for newer residential property | B57: 0.03 | C57: 0.03 | D57: 3% for buildings completed after 31.12.2022

Sheet 2025
A1: 🇩🇪 Complete German Income Tax Calculator — Tax Year 2025 | Blue cells = your inputs
A2: COLOUR GUIDE: 🔵 Blue = your input | 🟢 Green = auto-calculated | Yellow bg = input area | Blue bg = result | All amounts in EUR
A4: RATES REFERENCE — Auto-pulled from 'Rates' sheet for 2025 (change rates there if needed)
A6: SECTION 0 — PERSONAL DETAILS (affects tax class, allowances, surcharges)
A7: Tax class (Steuerklasse): 1=Single, 2=Single parent, 3=Married high earner, 4=Married equal, 5=Married low earner | K7: 1 | L7: 1=Single/divorced/widowed. Affects monthly withholding only, not final liability.
A8: Church tax applicable? Enter 1 for YES, 0 for NO | K8: 0 | L8: If registered with Catholic/Protestant church. Rate varies by state (8% Bavaria/BW, 9% others).
A9: Number of children under 25 (for care insurance & child allowance) | K9: 0 | L9: Affects long-term care rate (−0.25% per child from 2nd). Also drives Kinderfreibetrag.
A10: Degree of disability (GdB): 0 if none, else 20/30/40/50/60/70/80/90/100 | K10: 0 | L10: Grants flat-rate deduction (Behinderten-Pauschbetrag). GdB 50=€1,140, 100=€2,840.
A11: Blind or severely disabled with care needs? Enter 1 for YES, 0 for NO | K11: 0 | L11: Additional Pflegepauschbetrag or Blindenpauschbetrag may apply.
A12: Months resident/employed in Germany (12 if full year) | K12: 12 | L12: Pro-rates Grundfreibetrag for part-year residents. Usually 12.
A15: SECTION 1 — ALL INCOME SOURCES (§2 EStG — enter what applies to you)
A16: 1A EMPLOYMENT INCOME (Einkünfte aus nichtselbstständiger Arbeit — §19 EStG)
A17: Monthly gross salary — enter 0 for months not worked | K17: TOTAL | L17: Annual salary if all 12 months = monthly × 12
B18: Jan | C18: Feb | D18: Mar | E18: Apr | F18: May | G18: Jun | H18: Jul | I18: Aug | J18: Sep | K18: Annual | L18: Nov | M18: Dec | N18: Annual | O18: Oct | P18: Nov | Q18: Dec
A19: Primary employer (Hauptarbeitgeber) | B19: 0 | C19: 0 | D19: 6667 | E19: 6667 | F19: 6667 | G19: 6667 | H19: 6667 | I19: 6667 | J19: 6667 | K19: =N19 -> 66670 | N19: =SUM(B19:J19)+SUM(O19:Q19) -> 66670 | O19: 6667 | P19: 6667 | Q19: 6667
A20: Secondary employer / mini-job (if any) | B20: 0 | C20: 0 | D20: 0 | E20: 0 | F20: 0 | G20: 0 | H20: 0 | I20: 0 | J20: 0 | K20: =N20 -> 0 | N20: =SUM(B20:J20)+SUM(O20:Q20) -> 0 | O20: 0 | P20: 0 | Q20: 0
A21: Severance / termination payment (Abfindung) | B21: 0 | C21: 0 | D21: 0 | E21: 0 | F21: 0 | G21: 0 | H21: 0 | I21: 0 | J21: 0 | K21: =N21 -> 0 | N21: =SUM(B21:J21)+SUM(O21:Q21) -> 0 | O21: 0 | P21: 0 | Q21: 0
A22: Bonus / 13th month salary (Einmalzahlungen) | B22: 0 | C22: 0 | D22: 0 | E22: 0 | F22: 0 | G22: 0 | H22: 0 | I22: 0 | J22: 0 | K22: =N22 -> 0 | N22: =SUM(B22:J22)+SUM(O22:Q22) -> 0 | O22: 0 | P22: 0 | Q22: 0
A23: Employer reimbursements received (tax-free allowances e.g. Verpflegungsmehraufwand, tools) | K23: 0 | L23: Tax-free employer payments — do NOT add to taxable income. List here for awareness only.
A24: TOTAL GROSS EMPLOYMENT INCOME | K24: =SUM(K19:K22) -> 66670 | L24: Sum of all employment sources
A26: 1B SELF-EMPLOYMENT / FREELANCE INCOME (Einkünfte aus selbstständiger Arbeit — §18 EStG)
A27: Freelance / consulting revenue (gross) | K27: 0 | L27: Before business expenses. Declare in Anlage S.
A28: Business expenses (Betriebsausgaben) — allowable deductions | K28: 0 | L28: Equipment, software, professional fees, travel for client work, etc.
A29: Net freelance income | K29: =MAX(0,K27-K28) -> 0 | L29: Revenue minus business expenses
A31: 1C TRADE / BUSINESS INCOME (Einkünfte aus Gewerbebetrieb — §15 EStG)
A32: Business profit (Gewinn) — after all business expenses | K32: 0 | L32: Declare in Anlage G. Subject to trade tax (Gewerbesteuer) separately.
A33: Trade tax credit (Gewerbesteuer-Anrechnung §35 EStG) | K33: 0 | L33: 3.8 × trade tax base rate offsets income tax. Enter credit amount.
A35: 1D RENTAL & LEASING INCOME (Einkünfte aus Vermietung — §21 EStG)
A36: Total rental income received (gross, all properties) | K36: 0 | L36: Include all rent + ancillary cost reimbursements received.
A37: Mortgage interest on rental property (Schuldzinsen) | K37: 0 | L37: Fully deductible against rental income.
A38: Depreciation (AfA) — enter annual amount | K38: 0 | L38: 2% (old) or 3% (post-2022) of building value. Rates sheet has rates.
A39: Maintenance & repair costs (Erhaltungsaufwand) | K39: 0 | L39: Fully deductible. Large one-offs can be spread over 2-5 years.
A40: Property management fees, insurance, property tax | K40: 0 | L40: Hausverwaltung, Versicherung, Grundsteuer — all deductible.
A41: Other rental expenses (advertising, legal, travel to property) | K41: 0 | L41: All provable expenses incurred to generate rental income.
A42: Net rental income / loss | K42: =MAX(-999999,K36-K37-K38-K39-K40-K41) -> 0 | L42: Can be negative (Verlustvortrag). Losses offset other income.
A44: 1E CAPITAL INVESTMENT INCOME (Einkünfte aus Kapitalvermögen — §20 EStG)
A45: Dividends from German companies (gross, before KESt) | K45: 0 | L45: German dividends taxed at 25% Abgeltungsteuer. Already withheld by bank.
A46: Dividends from foreign companies (gross) | K46: 0 | L46: Foreign withholding tax may be offset via Anlage KAP.
A47: Interest income — savings, bonds, P2P lending (gross) | K47: 200 | L47: Bank savings, Tagesgeld, Festgeld, bonds. Withheld at 25%.
A48: ETF / fund distributions (Ausschüttungen, gross) | K48: 0 | L48: Includes Vorabpauschale for accumulating funds (auto-calculated by broker).
A49: Realised gains from selling shares/ETFs (gross profit) | K49: 0 | L49: Purchase price minus selling price. Enter net gain (after losses netted).
A50: Capital losses to offset (Verlustverrechnungstopf) | K50: 0 | L50: Losses from stock sales offset gains. Bank tracks automatically.
A51: Foreign withholding tax already paid (on foreign dividends) | K51: 0 | L51: Creditable against German Abgeltungsteuer (up to 15% per treaty).
A52: Total gross capital income | K52: =MAX(0,K45+K46+K47+K48+K49-K50) -> 200 | L52: Before allowance deduction
A53: Sparer-Pauschbetrag (saver's allowance) | K53: =MIN(K52,Rates!B56) -> 0.02 | L53: Deducted from capital income. Ref: Rates sheet.
A54: Taxable capital income (after allowance) | K54: =MAX(0,K52-K53) -> 199.98 | L54: Subject to 25% Abgeltungsteuer
A55: Capital gains tax (Abgeltungsteuer 25%) | K55: =ROUND(K54*Rates!B114,2) -> 0 | L55: 25% flat
A56: Soli on capital gains tax (5.5%) | K56: =ROUND(K55*Rates!B115,2) -> 0 | L56: Always 5.5% (no exemption for capital gains Soli)
A57: Church tax on capital gains (if applicable) | K57: =IF(K8=1,ROUND(K55*Rates!B11,2),0) -> 0 | L57: Only if church registered
A58: Foreign tax credit on capital gains (reduces tax) | K58: =MIN(K55,K51) -> 0 | L58: Foreign WHT credited against German Abgeltungsteuer
A59: TOTAL TAX ON CAPITAL INCOME | K59: =ROUND(K55+K56+K57-K58,2) -> 0 | L59: Note: Capital income is NOT added to income for progressive tax (unless Günstigerprüfung elected)
A60: Elect Günstigerprüfung? (1=YES if your progressive rate < 25%) | K60: 0 | L60: If your marginal tax rate < 25%, fold capital income into progressive tax — can reduce overall tax. Set =1 to add capital income to zvE below.
A62: 1F OTHER INCOME (Sonstige Einkünfte — §22 EStG)
A63: Statutory pension income (gesetzliche Rente, taxable portion) | K63: 0 | L63: Only taxable portion (depends on year pension started). Enter already-adjusted taxable amount.
A64: Private pension / annuity payments (Leibrente, ertragsanteil only) | K64: 0 | L64: Only the Ertragsanteil is taxable — check your pension statement.
A65: Maintenance/alimony received (Unterhalt, if Realsplitting elected) | K65: 0 | L65: Taxable if payer deducts as Sonderausgaben. Declare in Anlage SO.
A66: Private sale gains within holding period (Spekulationsgewinne §23) | K66: 0 | L66: Property sold < 10 years (unless owner-occupied). Stocks/crypto < 1 year.
A67: Cryptocurrency gains (taxable if held < 1 year, §23 EStG) | K67: 0 | L67: Tax-free if held > 1 year. < 1 year: taxed at progressive rate as other income.
A68: Other miscellaneous income (§22 EStG) | K68: 0 | L68: Occasional income, subletting income above threshold, etc.
A69: Total other income | K69: =K63+K64+K65+K66+K67+K68 -> 0
A71: TOTAL GROSS INCOME (Gesamtbetrag aller Einkünfte) | K71: =K24+K29+K32+K42+IF(K60=1,K52,0)+K69 -> 66670 | L71: All income streams combined (capital income added only if Günstigerprüfung elected)
A74: SECTION 2 — EMPLOYMENT DEDUCTIONS (Werbungskosten — §9 EStG)
A75: 2A COMMUTING (Pendlerpauschale / Entfernungspauschale)
A76: One-way distance to workplace (km) | K76: 8 | L76: Enter distance in km (one-way only, not return).
A77: Actual commuting days to office per year (not WFH days) | K77: 241 | L77: Full-year employed = 230 average. Adjust for part-year.
A78: Actual ticket cost (annual) — e.g. Deutschlandticket | K78: 756 | L78: €63 × 12 = €756. Deduct actual cost if higher than km allowance.
A79: Commuting allowance (km-based formula) | K79: =IF(K76<=Rates!B114,K77*K76*Rates!B112,K77*(Rates!B114*Rates!B112+(K76-Rates!B114)*Rates!B113)) -> 0 | L79: 2025: 30¢ first 20km, 38¢ beyond
A80: Commuting deduction (higher of km-allowance vs actual ticket) | K80: =MAX(K79,K78) -> 756 | L80: Takes the higher of the two — Deutschland Ticket usually wins
A82: 2B HOME OFFICE (Homeoffice-Pauschale — §4 Abs.5 EStG)
A83: WFH days exclusively at home (max 210) | K83: 124 | L83: Max 210 days × €6 = €1,260. Cannot combine with commuting for same day.
A84: Home office deduction (Homeoffice-Pauschale) | K84: =MIN(K83,210)*Rates!B110 -> 0 | L84: Min(days,210) × €6
A85: Dedicated home office room costs (Arbeitszimmer) — if applicable | K85: 0 | L85: If home office is centre of work: actual costs OR €1,260 flat. Cannot combine with Homeoffice-Pauschale.
A86: Home office total (Pauschale OR Arbeitszimmer, not both) | K86: =MAX(K84,K85) -> 0 | L86: Uses whichever is higher — cannot claim both
A88: 2C WORK EQUIPMENT (Arbeitsmittel — §9 Abs.1 Nr.6 EStG)
A89: Computer / laptop (50% of cost, or 100% if exclusively work) | K89: 400 | L89: 50% default without proof. Items ≤ €800 net: deduct in full in purchase year.
A90: Smartphone (work-use portion, usually 50%) | K90: 0 | L90: 50% default without proof. Enter your portion.
A91: Desk, office chair, monitor, peripherals | K91: 60 | L91: Items ≤ €800 net each: deduct 100% in purchase year.
A92: Software, subscriptions for work (annual) | K92: 0 | L92: Work-related software licences, cloud storage for work, etc.
A93: Other work tools, PPE, briefcase, uniform cleaning | K93: 0 | L93: Work clothes must be mandatory uniform — not civilian clothes.
A94: Professional books, journals, magazines | K94: 0 | L94: Must be directly work-related.
A95: Total work equipment deduction | K95: =K89+K90+K91+K92+K93+K94 -> 460
A97: 2D COMMUNICATIONS (Internet, Phone)
A98: Monthly internet + phone bill (total) | K98: 10 | L98: Max deductible: 20% of bill, capped at €20/month.
A99: Internet/phone deduction (12 months) | K99: =MIN(Rates!B115,ROUND(K98*Rates!B116,2))*12 -> 0 | L99: Min(€20, 20% of bill) × 12
A101: 2E BUSINESS TRAVEL & TRAINING
A102: Business trips / client visits (actual costs: transport, hotel) | K102: 0 | L102: Meals deductible as Verpflegungsmehraufwand: €14/day domestic (<8h), €28/day (>8h).
A103: Job-related training & education (Fortbildungskosten) | K103: 0 | L103: Courses, certifications, conferences for your current job.
A104: Job application costs (postage, photos, travel to interviews) | K104: 0 | L104: If actively job-seeking. Usually small amount.
A106: 2F UNION / PROFESSIONAL MEMBERSHIP
A107: Trade union dues (Gewerkschaftsbeiträge) | K107: 0 | L107: Fully deductible as Werbungskosten.
A108: Professional association memberships | K108: 0 | L108: Must be directly related to your profession.
A110: 2G DOUBLE HOUSEHOLD (Doppelte Haushaltsführung — §9 Abs.1 Nr.5)
A111: Double household costs (second residence near work, max €1,000/month) | K111: 0 | L111: Rent + utilities for work-required second home. Max €1,000/month = €12,000/year.
A112: Weekly trips home (km × 2 × weeks × rate per km) | K112: 0 | L112: One weekly trip home per week deductible at commuting rate.
A114: TOTAL ACTUAL WERBUNGSKOSTEN | K114: =K80+K86+K95+K99+K102+K103+K104+K107+K108+K111+K112 -> 1216
A115: Effective Werbungskosten (MAX of actual vs flat-rate €1,230) | K115: =MAX(K114,Rates!B49) -> 1216 | L115: Only the excess above €1,230 saves tax (€1,230 is automatic)
A118: SECTION 3 — SPECIAL EXPENSES (Sonderausgaben — §10 EStG)
A119: 3A PENSION & RETIREMENT CONTRIBUTIONS
A120: Statutory pension contribution (employee share, paid by employer) | K120: 0 | L120: Usually auto-deducted. Use actual figure from Lohnsteuerbescheinigung. Fully deductible 2025+.
A121: Riester pension contributions (own payments) | K121: 0 | L121: Max €2,100/year eligible for Riester-Zulage or tax deduction, whichever better.
...

Sheet 2026
A1: 🇩🇪 Complete German Income Tax Calculator — Tax Year 2026 | Blue cells = your inputs
A2: COLOUR GUIDE: 🔵 Blue = your input | 🟢 Green = auto-calculated | Yellow bg = input area | Blue bg = result | All amounts in EUR
A4: RATES REFERENCE — Auto-pulled from 'Rates' sheet for 2026 (change rates there if needed)
A6: SECTION 0 — PERSONAL DETAILS (affects tax class, allowances, surcharges)
A7: Tax class (Steuerklasse): 1=Single, 2=Single parent, 3=Married high earner, 4=Married equal, 5=Married low earner | K7: 1 | L7: 1=Single/divorced/widowed. Affects monthly withholding only, not final liability.
A8: Church tax applicable? Enter 1 for YES, 0 for NO | K8: 0 | L8: If registered with Catholic/Protestant church. Rate varies by state (8% Bavaria/BW, 9% others).
A9: Number of children under 25 (for care insurance & child allowance) | K9: 0 | L9: Affects long-term care rate (−0.25% per child from 2nd). Also drives Kinderfreibetrag.
A10: Degree of disability (GdB): 0 if none, else 20/30/40/50/60/70/80/90/100 | K10: 0 | L10: Grants flat-rate deduction (Behinderten-Pauschbetrag). GdB 50=€1,140, 100=€2,840.
A11: Blind or severely disabled with care needs? Enter 1 for YES, 0 for NO | K11: 0 | L11: Additional Pflegepauschbetrag or Blindenpauschbetrag may apply.
A12: Months resident/employed in Germany (12 if full year) | K12: 12 | L12: Pro-rates Grundfreibetrag for part-year residents. Usually 12.
A15: SECTION 1 — ALL INCOME SOURCES (§2 EStG — enter what applies to you)
A16: 1A EMPLOYMENT INCOME (Einkünfte aus nichtselbstständiger Arbeit — §19 EStG)
A17: Monthly gross salary — enter 0 for months not worked | K17: TOTAL | L17: Annual salary if all 12 months = monthly × 12
B18: Jan | C18: Feb | D18: Mar | E18: Apr | F18: May | G18: Jun | H18: Jul | I18: Aug | J18: Sep | K18: Annual | L18: Nov | M18: Dec | N18: Annual | O18: Oct | P18: Nov | Q18: Dec
A19: Primary employer (Hauptarbeitgeber) | B19: 6667 | C19: 6667 | D19: 6667 | E19: 7708 | F19: 7708 | G19: 7708 | H19: 7708 | I19: 7708 | J19: 7708 | K19: =N19 -> 89373 | N19: =SUM(B19:J19)+SUM(O19:Q19) -> 89373 | O19: 7708 | P19: 7708 | Q19: 7708
A20: Secondary employer / mini-job (if any) | B20: 0 | C20: 0 | D20: 0 | E20: 0 | F20: 0 | G20: 0 | H20: 0 | I20: 0 | J20: 0 | K20: =N20 -> 0 | N20: =SUM(B20:J20)+SUM(O20:Q20) -> 0 | O20: 0 | P20: 0 | Q20: 0
A21: Severance / termination payment (Abfindung) | B21: 0 | C21: 0 | D21: 0 | E21: 0 | F21: 0 | G21: 0 | H21: 0 | I21: 0 | J21: 0 | K21: =N21 -> 0 | N21: =SUM(B21:J21)+SUM(O21:Q21) -> 0 | O21: 0 | P21: 0 | Q21: 0
A22: Bonus / 13th month salary (Einmalzahlungen) | B22: 0 | C22: 0 | D22: 0 | E22: 0 | F22: 0 | G22: 0 | H22: 0 | I22: 0 | J22: 0 | K22: =N22 -> 0 | N22: =SUM(B22:J22)+SUM(O22:Q22) -> 0 | O22: 0 | P22: 0 | Q22: 0
A23: Employer reimbursements received (tax-free allowances e.g. Verpflegungsmehraufwand, tools) | K23: 0 | L23: Tax-free employer payments — do NOT add to taxable income. List here for awareness only.
A24: TOTAL GROSS EMPLOYMENT INCOME | K24: =SUM(K19:K22) -> 89373 | L24: Sum of all employment sources
A26: 1B SELF-EMPLOYMENT / FREELANCE INCOME (Einkünfte aus selbstständiger Arbeit — §18 EStG)
A27: Freelance / consulting revenue (gross) | K27: 0 | L27: Before business expenses. Declare in Anlage S.
A28: Business expenses (Betriebsausgaben) — allowable deductions | K28: 0 | L28: Equipment, software, professional fees, travel for client work, etc.
A29: Net freelance income | K29: =MAX(0,K27-K28) -> 0 | L29: Revenue minus business expenses
A31: 1C TRADE / BUSINESS INCOME (Einkünfte aus Gewerbebetrieb — §15 EStG)
A32: Business profit (Gewinn) — after all business expenses | K32: 0 | L32: Declare in Anlage G. Subject to trade tax (Gewerbesteuer) separately.
A33: Trade tax credit (Gewerbesteuer-Anrechnung §35 EStG) | K33: 0 | L33: 3.8 × trade tax base rate offsets income tax. Enter credit amount.
A35: 1D RENTAL & LEASING INCOME (Einkünfte aus Vermietung — §21 EStG)
A36: Total rental income received (gross, all properties) | K36: 0 | L36: Include all rent + ancillary cost reimbursements received.
A37: Mortgage interest on rental property (Schuldzinsen) | K37: 0 | L37: Fully deductible against rental income.
A38: Depreciation (AfA) — enter annual amount | K38: 0 | L38: 2% (old) or 3% (post-2022) of building value. Rates sheet has rates.
A39: Maintenance & repair costs (Erhaltungsaufwand) | K39: 0 | L39: Fully deductible. Large one-offs can be spread over 2-5 years.
A40: Property management fees, insurance, property tax | K40: 0 | L40: Hausverwaltung, Versicherung, Grundsteuer — all deductible.
A41: Other rental expenses (advertising, legal, travel to property) | K41: 0 | L41: All provable expenses incurred to generate rental income.
A42: Net rental income / loss | K42: =MAX(-999999,K36-K37-K38-K39-K40-K41) -> 0 | L42: Can be negative (Verlustvortrag). Losses offset other income.
A44: 1E CAPITAL INVESTMENT INCOME (Einkünfte aus Kapitalvermögen — §20 EStG)
A45: Dividends from German companies (gross, before KESt) | K45: 0 | L45: German dividends taxed at 25% Abgeltungsteuer. Already withheld by bank.
A46: Dividends from foreign companies (gross) | K46: 0 | L46: Foreign withholding tax may be offset via Anlage KAP.
A47: Interest income — savings, bonds, P2P lending (gross) | K47: 200 | L47: Bank savings, Tagesgeld, Festgeld, bonds. Withheld at 25%.
A48: ETF / fund distributions (Ausschüttungen, gross) | K48: 0 | L48: Includes Vorabpauschale for accumulating funds (auto-calculated by broker).
A49: Realised gains from selling shares/ETFs (gross profit) | K49: 0 | L49: Purchase price minus selling price. Enter net gain (after losses netted).
A50: Capital losses to offset (Verlustverrechnungstopf) | K50: 0 | L50: Losses from stock sales offset gains. Bank tracks automatically.
A51: Foreign withholding tax already paid (on foreign dividends) | K51: 0 | L51: Creditable against German Abgeltungsteuer (up to 15% per treaty).
A52: Total gross capital income | K52: =MAX(0,K45+K46+K47+K48+K49-K50) -> 200 | L52: Before allowance deduction
A53: Sparer-Pauschbetrag (saver's allowance) | K53: =MIN(K52,Rates!C56) -> 0.02 | L53: Deducted from capital income. Ref: Rates sheet.
A54: Taxable capital income (after allowance) | K54: =MAX(0,K52-K53) -> 199.98 | L54: Subject to 25% Abgeltungsteuer
A55: Capital gains tax (Abgeltungsteuer 25%) | K55: =ROUND(K54*Rates!C114,2) -> 0 | L55: 25% flat
A56: Soli on capital gains tax (5.5%) | K56: =ROUND(K55*Rates!C115,2) -> 0 | L56: Always 5.5% (no exemption for capital gains Soli)
A57: Church tax on capital gains (if applicable) | K57: =IF(K8=1,ROUND(K55*Rates!C11,2),0) -> 0 | L57: Only if church registered
A58: Foreign tax credit on capital gains (reduces tax) | K58: =MIN(K55,K51) -> 0 | L58: Foreign WHT credited against German Abgeltungsteuer
A59: TOTAL TAX ON CAPITAL INCOME | K59: =ROUND(K55+K56+K57-K58,2) -> 0 | L59: Note: Capital income is NOT added to income for progressive tax (unless Günstigerprüfung elected)
A60: Elect Günstigerprüfung? (1=YES if your progressive rate < 25%) | K60: 0 | L60: If your marginal tax rate < 25%, fold capital income into progressive tax — can reduce overall tax. Set =1 to add capital income to zvE below.
A62: 1F OTHER INCOME (Sonstige Einkünfte — §22 EStG)
A63: Statutory pension income (gesetzliche Rente, taxable portion) | K63: 0 | L63: Only taxable portion (depends on year pension started). Enter already-adjusted taxable amount.
A64: Private pension / annuity payments (Leibrente, ertragsanteil only) | K64: 0 | L64: Only the Ertragsanteil is taxable — check your pension statement.
A65: Maintenance/alimony received (Unterhalt, if Realsplitting elected) | K65: 0 | L65: Taxable if payer deducts as Sonderausgaben. Declare in Anlage SO.
A66: Private sale gains within holding period (Spekulationsgewinne §23) | K66: 0 | L66: Property sold < 10 years (unless owner-occupied). Stocks/crypto < 1 year.
A67: Cryptocurrency gains (taxable if held < 1 year, §23 EStG) | K67: 0 | L67: Tax-free if held > 1 year. < 1 year: taxed at progressive rate as other income.
A68: Other miscellaneous income (§22 EStG) | K68: 0 | L68: Occasional income, subletting income above threshold, etc.
A69: Total other income | K69: =K63+K64+K65+K66+K67+K68 -> 0
A71: TOTAL GROSS INCOME (Gesamtbetrag aller Einkünfte) | K71: =K24+K29+K32+K42+IF(K60=1,K52,0)+K69 -> 89373 | L71: All income streams combined (capital income added only if Günstigerprüfung elected)
A74: SECTION 2 — EMPLOYMENT DEDUCTIONS (Werbungskosten — §9 EStG)
A75: 2A COMMUTING (Pendlerpauschale / Entfernungspauschale)
A76: One-way distance to workplace (km) | K76: 8 | L76: Enter distance in km (one-way only, not return).
A77: Actual commuting days to office per year (not WFH days) | K77: 241 | L77: Full-year employed = 230 average. Adjust for part-year.
A78: Actual ticket cost (annual) — e.g. Deutschlandticket | K78: 756 | L78: €63 × 12 = €756. Deduct actual cost if higher than km allowance.
A79: Commuting allowance (km-based formula) | K79: =K77*K76*Rates!C113 -> 0 | L79: 2026: 38¢/km from km 1
A80: Commuting deduction (higher of km-allowance vs actual ticket) | K80: =MAX(K79,K78) -> 756 | L80: Takes the higher of the two — Deutschland Ticket usually wins
A82: 2B HOME OFFICE (Homeoffice-Pauschale — §4 Abs.5 EStG)
A83: WFH days exclusively at home (max 210) | K83: 124 | L83: Max 210 days × €6 = €1,260. Cannot combine with commuting for same day.
A84: Home office deduction (Homeoffice-Pauschale) | K84: =MIN(K83,210)*Rates!C110 -> 0 | L84: Min(days,210) × €6
A85: Dedicated home office room costs (Arbeitszimmer) — if applicable | K85: 0 | L85: If home office is centre of work: actual costs OR €1,260 flat. Cannot combine with Homeoffice-Pauschale.
A86: Home office total (Pauschale OR Arbeitszimmer, not both) | K86: =MAX(K84,K85) -> 0 | L86: Uses whichever is higher — cannot claim both
A88: 2C WORK EQUIPMENT (Arbeitsmittel — §9 Abs.1 Nr.6 EStG)
A89: Computer / laptop (50% of cost, or 100% if exclusively work) | K89: 400 | L89: 50% default without proof. Items ≤ €800 net: deduct in full in purchase year.
A90: Smartphone (work-use portion, usually 50%) | K90: 0 | L90: 50% default without proof. Enter your portion.
A91: Desk, office chair, monitor, peripherals | K91: 60 | L91: Items ≤ €800 net each: deduct 100% in purchase year.
A92: Software, subscriptions for work (annual) | K92: 0 | L92: Work-related software licences, cloud storage for work, etc.
A93: Other work tools, PPE, briefcase, uniform cleaning | K93: 0 | L93: Work clothes must be mandatory uniform — not civilian clothes.
A94: Professional books, journals, magazines | K94: 0 | L94: Must be directly work-related.
A95: Total work equipment deduction | K95: =K89+K90+K91+K92+K93+K94 -> 460
A97: 2D COMMUNICATIONS (Internet, Phone)
A98: Monthly internet + phone bill (total) | K98: 10 | L98: Max deductible: 20% of bill, capped at €20/month.
A99: Internet/phone deduction (12 months) | K99: =MIN(Rates!C115,ROUND(K98*Rates!C116,2))*12 -> 0 | L99: Min(€20, 20% of bill) × 12
A101: 2E BUSINESS TRAVEL & TRAINING
A102: Business trips / client visits (actual costs: transport, hotel) | K102: 0 | L102: Meals deductible as Verpflegungsmehraufwand: €14/day domestic (<8h), €28/day (>8h).
A103: Job-related training & education (Fortbildungskosten) | K103: 0 | L103: Courses, certifications, conferences for your current job.
A104: Job application costs (postage, photos, travel to interviews) | K104: 0 | L104: If actively job-seeking. Usually small amount.
A106: 2F UNION / PROFESSIONAL MEMBERSHIP
A107: Trade union dues (Gewerkschaftsbeiträge) | K107: 0 | L107: Fully deductible as Werbungskosten.
A108: Professional association memberships | K108: 0 | L108: Must be directly related to your profession.
A110: 2G DOUBLE HOUSEHOLD (Doppelte Haushaltsführung — §9 Abs.1 Nr.5)
A111: Double household costs (second residence near work, max €1,000/month) | K111: 0 | L111: Rent + utilities for work-required second home. Max €1,000/month = €12,000/year.
A112: Weekly trips home (km × 2 × weeks × rate per km) | K112: 0 | L112: One weekly trip home per week deductible at commuting rate.
A114: TOTAL ACTUAL WERBUNGSKOSTEN | K114: =K80+K86+K95+K99+K102+K103+K104+K107+K108+K111+K112 -> 1216
A115: Effective Werbungskosten (MAX of actual vs flat-rate €1,230) | K115: =MAX(K114,Rates!C49) -> 1216 | L115: Only the excess above €1,230 saves tax (€1,230 is automatic)
A118: SECTION 3 — SPECIAL EXPENSES (Sonderausgaben — §10 EStG)
A119: 3A PENSION & RETIREMENT CONTRIBUTIONS
A120: Statutory pension contribution (employee share, paid by employer) | K120: 0 | L120: Usually auto-deducted. Use actual figure from Lohnsteuerbescheinigung. Fully deductible 2025+.
A121: Riester pension contributions (own payments) | K121: 0 | L121: Max €2,100/year eligible for Riester-Zulage or tax deduction, whichever better.
...

Sheet 📋 Instructions
A1: 🇩🇪 Complete German Tax Calculator — Instructions & Legend
A2: COLOUR CODING
A3: 🔵 Blue text + yellow background | B3: YOUR INPUT — change these cells to match your situation
A4: 🟢 Green text + blue background | B4: AUTO-CALCULATED — do not edit
A5: ⚫ Black text + grey/white background | B5: Totals and section labels
A7: HOW TO USE THIS WORKBOOK
A8: Step 1 | B8: Go to the 'Rates' sheet. All official 2025 and 2026 rates are pre-filled. You can adjust if rates change.
A9: Step 2 | B9: Go to '2025' or '2026' sheet. Start at Section 0 — fill in your personal details (tax class, children, disability).
A10: Step 3 | B10: Section 1 — Enter your monthly salaries. Set months you did not work to 0. Add freelance, rental, capital income if applicable.
A11: Step 4 | B11: Section 2 — Enter your Werbungskosten. Many items pre-filled from our conversation. Add/change as needed.
A12: Step 5 | B12: Section 3 — Enter Sonderausgaben. Most items are 0 unless you have pension contributions, donations, childcare, etc.
A13: Step 6 | B13: Section 4 — Enter extraordinary burdens (medical, disability, care) only if they apply to you.
A14: Step 7 | B14: Section 5 — Social security is auto-calculated. No input needed.
A15: Step 8 | B15: Section 6 — Enter loss carry-forwards from prior years (usually 0 unless you had losses).
A16: Step 9 | B16: Sections 7-9 — Review taxable income, income tax, total burden. All auto-calculated.
A17: Step 10 | B17: Section 10 — After year end, enter actual Lohnsteuer withheld from your Lohnsteuerbescheinigung (employer tax certificate). This gives your refund/payment.
A18: Step 11 | B18: Section 11 — Review the dashboard for effective rates and summary.
A20: INCOME TYPES COVERED
A21: §19 Employment | B21: Salary from all jobs, bonuses, severance pay
A22: §18 Self-employment | B22: Freelance, consulting, professional services
A23: §15 Trade/business | B23: Business income (Gewerbebetrieb)
A24: §21 Rental | B24: Rental income net of expenses, depreciation, interest
A25: §20 Capital income | B25: Dividends, interest, ETF gains, with Abgeltungsteuer
A26: §22 Other income | B26: Pension, private annuity, maintenance, crypto, speculation
A28: DEDUCTIONS COVERED
A29: Werbungskosten §9 | B29: Commuting, home office, equipment, internet, travel, training, union dues, double household
A30: Sonderausgaben §10 | B30: Pension contributions, health insurance, childcare, school fees, donations, church tax, maintenance paid
A31: Außergewöhnliche Belastungen §33 | B31: Medical, funeral, care costs above reasonable threshold
A32: Flat-rate deductions §33a/b | B32: Disability (Behinderten-Pauschbetrag), blindness, care-giving flat rate
A33: Loss offsets §10d | B33: Carry-forward and carry-back of losses from prior years
A35: IMPORTANT NOTES
A36: Tax formula | B36: Uses §32a EStG progressive formula — approximation. Always verify final amount at bmf-steuerrechner.de or via ELSTER.
A37: Günstigerprüfung | B37: Capital income is normally taxed separately at 25%. If your marginal rate < 25%, set flag in Section 1E to add it to progressive income — may reduce total tax.
A38: Kinderfreibetrag | B38: Child allowance (Kinderfreibetrag) is compared by Finanzamt against Kindergeld received — they automatically apply whichever is better.
A39: Lohnsteuerbescheinigung | B39: The refund calculation requires your actual Lohnsteuer withheld. This is on your employer's tax certificate (Lohnsteuerbescheinigung), issued by end of February following the tax year.
A40: Freistellungsauftrag | B40: Submit a Freistellungsauftrag to your bank(s) to use your Sparer-Pauschbetrag (€1,000 single) so they don't withhold KESt automatically.
A41: Disclaimer | B41: This calculator is for estimation and planning purposes only. It is not tax advice. Always verify your final return using ELSTER or consult a Steuerberater.
